colourpick/__init__.py
colourpick/clusterpick.py
colourpick-1.0.2.dist-info/LICENSE.txt
colourpick-1.0.2.dist-info/METADATA
colourpick-1.0.2.dist-info/WHEEL
colourpick-1.0.2.dist-info/top_level.txt
colourpick-1.0.2.dist-info/RECORD
